{
  "name": "scholarlens",
  "version": "1.0.0",
  "private": true,
  "scripts": {
"start": "concurrently \"npm --prefix backend start\" \"npx live-server frontend\" \"npm run start:ml\"",
"start:ml": "python ml_service/app.py"    "start:ml": "python ml_service/app.py",
    "start:full": "concurrently \"npm --prefix backend start\" \"npx live-server frontend\" \"python ml_service/app.py\"",
    "seed:sample-data": "node backend/scripts/seedSampleData.js",
    "export:ml-data": "node backend/scripts/exportMlDataset.js",
    "train:ml": "python ml_service/train.py"
  },
  "devDependencies": {
    "concurrently": "^9.2.1",
    "live-server": "^1.2.2"
  }
}
